setup.cfg
setup.py
bluejay/__init__.py
bluejay/bluejay.py
bluejay/openstack.py
bluejay2.egg-info/PKG-INFO
bluejay2.egg-info/SOURCES.txt
bluejay2.egg-info/dependency_links.txt
bluejay2.egg-info/entry_points.txt
bluejay2.egg-info/requires.txt
bluejay2.egg-info/top_level.txt