Metadata-Version: 1.0
Name: bluejay2
Version: 0.1.5
Summary: Client for Nibiru
Home-page: UNKNOWN
Author: Dinesh Weerapurage
Author-email: dinesh.weerapurage@pearson.com
License: UNKNOWN
Platform: UNKNOWN
